projects/__init__.py
projects/conf.py
projects/forms.py
projects/helpers.py
projects/models.py
projects/nav.py
projects/views.py
projects/static/nbi_projects_style.css
projects/static/projects.js
projects/static/images/bohrium_logo.png
projects/templates/projects/_projects_base.html
projects/templates/projects/create_project.html
projects/templates/projects/login.html
projects/templates/projects/project.html
projects/templates/projects/projects.html
projects/templates/projects/reset_password_form.html
projects/templates/projects/email/activate_user.html
projects/templates/projects/email/reset_password.html
projects/tests/__init__.py
projects/tests/test_projects.py
projects_base/__init__.py
projects_base/base/__init__.py
projects_base/base/conf.py
projects_base/base/forms.py
projects_base/base/models.py
projects_base/base/views.py
projects_base/base/static/common.js
projects_base/base/static/default_style.css
projects_base/base/static/gif/dark_green_loader.gif
projects_base/base/static/gif/light_green_loader.gif
projects_base/base/templates/base/_formhelpers.html
projects_base/base/templates/base/base.html
projects_base/base/templates/base/create.html
projects_base/base/templates/base/grid.html
projects_base/base/templates/base/highlight_tags_section.html
projects_base/base/templates/base/search_section.html
projects_base/base/templates/base/show.html
projects_base/base/templates/base/table.html
projects_base/res/config.ini
projects_site-0.1.5.dist-info/LICENSE
projects_site-0.1.5.dist-info/METADATA
projects_site-0.1.5.dist-info/WHEEL
projects_site-0.1.5.dist-info/top_level.txt
projects_site-0.1.5.dist-info/RECORD
