Metadata-Version: 2.1
Name: projects-site
Version: 0.1.5
Summary: 
Home-page: https://github.com/rasmunk/projects-site
Author: Rasmus Munk
Author-email: rasmus.munk@nbi.ku.dk
License: UNKNOWN
Keywords: Website,Flask,MetaData
Platform: UNKNOWN
Classifier: Programming Language :: Python :: 3.6
Classifier: Programming Language :: Python :: 3.7
Requires-Dist: Flask
Requires-Dist: flask-bootstrap
Requires-Dist: flask-nav
Requires-Dist: flask-wtf
Requires-Dist: wtforms
Requires-Dist: requests
Requires-Dist: wtforms-components
Requires-Dist: flask-login
Requires-Dist: flask-mail
Requires-Dist: bcrypt
Requires-Dist: configparser
Requires-Dist: email-validator
